gitactions/__init__.py
gitactions/_version.py
gitactions/main.py
gitactions/utils/__init__.py
gitactions/utils/log_utils.py
gitactions-0.11.7.dist-info/licenses/LICENSE
gitactions-0.11.7.dist-info/METADATA
gitactions-0.11.7.dist-info/WHEEL
gitactions-0.11.7.dist-info/top_level.txt
gitactions-0.11.7.dist-info/RECORD
